batchup/__init__.py
batchup/config.py
batchup/data_source.py
batchup/sampling.py
batchup/work_pool.py
batchup/datasets/__init__.py
batchup/datasets/cifar10.py
batchup/datasets/cifar100.py
batchup/datasets/dataset.py
batchup/datasets/fashion_mnist.py
batchup/datasets/mnist.py
batchup/datasets/stl.py
batchup/datasets/svhn.py
batchup/datasets/usps.py
batchup/image/__init__.py
batchup/image/utils.py
batchup/tests/__init__.py
batchup/tests/conftest.py
batchup/tests/dataset_test_helpers.py
batchup/tests/test_cifar10.py
batchup/tests/test_cifar100.py
batchup/tests/test_config.py
batchup/tests/test_data_source.py
batchup/tests/test_dataset.py
batchup/tests/test_fashion_mnist.py
batchup/tests/test_image_utils.py
batchup/tests/test_mnist.py
batchup/tests/test_sampling.py
batchup/tests/test_stl.py
batchup/tests/test_svhn.py
batchup/tests/test_usps.py
batchup/tests/test_work_pool.py
batchup-0.2.3.dist-info/LICENSE
batchup-0.2.3.dist-info/METADATA
batchup-0.2.3.dist-info/WHEEL
batchup-0.2.3.dist-info/top_level.txt
batchup-0.2.3.dist-info/RECORD
