Metadata-Version: 2.1
Name: batchup
Version: 0.2.3
Summary: Python library for extracting mini-batches of data from a data source for the purpose of training neural networks
Home-page: https://github.com/Britefury/batchup
Author: Geoffrey French
License: MIT
Platform: UNKNOWN
Classifier: Development Status :: 3 - Alpha
Classifier: Intended Audience :: Developers
Classifier: Intended Audience :: Science/Research
Classifier: License :: OSI Approved :: MIT License
Classifier: Programming Language :: Python :: 2.7
Classifier: Programming Language :: Python :: 3.6
Classifier: Topic :: Scientific/Engineering :: Artificial Intelligence
Requires-Dist: numpy
Requires-Dist: scipy
Requires-Dist: six
Requires-Dist: tables
Requires-Dist: joblib
Provides-Extra: testing
Requires-Dist: mock ; extra == 'testing'
Requires-Dist: pytest ; extra == 'testing'
Requires-Dist: pytest-cov ; extra == 'testing'
Requires-Dist: pytest-pep8 ; extra == 'testing'
